[{"type":"interface","namespace":"\\Drupal\\Core\\Config","meta":{"file":"\/Users\/clemens\/Sites\/drupal\/d8\/www\/core\/lib\/Drupal\/Core\/Config\/StorageComparerInterface.php","output":"\/Users\/clemens\/Sites\/drupal-devs\/uml-generator-php\/animations\/drupal-8\/core\/lib\/Drupal\/Core\/Config\/StorageComparerInterface.json"},"name":"StorageComparerInterface","children":[{"type":"method","name":"getSourceStorage","scope":"instance","parameters":[{"name":"collection","type":null}],"visibility":"public"},{"type":"method","name":"getTargetStorage","scope":"instance","parameters":[{"name":"collection","type":null}],"visibility":"public"},{"type":"method","name":"getEmptyChangelist","scope":"instance","parameters":[],"visibility":"public"},{"type":"method","name":"getChangelist","scope":"instance","parameters":[{"name":"op","type":null},{"name":"collection","type":null}],"visibility":"public"},{"type":"method","name":"reset","scope":"instance","parameters":[],"visibility":"public"},{"type":"method","name":"hasChanges","scope":"instance","parameters":[],"visibility":"public"},{"type":"method","name":"validateSiteUuid","scope":"instance","parameters":[],"visibility":"public"},{"type":"method","name":"moveRenameToUpdate","scope":"instance","parameters":[{"name":"rename","type":null},{"name":"collection","type":null}],"visibility":"public"},{"type":"method","name":"extractRenameNames","scope":"instance","parameters":[{"name":"name","type":null}],"visibility":"public"},{"type":"method","name":"getAllCollectionNames","scope":"instance","parameters":[{"name":"include_default","type":null}],"visibility":"public"}]}]