[{"type":"interface","namespace":"\\Drupal\\migrate\\Plugin","meta":{"file":"\/Users\/clemens\/Sites\/drupal\/d8\/www\/core\/modules\/migrate\/src\/Plugin\/MigrateSourceInterface.php","output":"\/Users\/clemens\/Sites\/drupal-devs\/uml-generator-php\/animations\/drupal-8\/core\/modules\/migrate\/src\/Plugin\/MigrateSourceInterface.json"},"name":"MigrateSourceInterface","children":[{"type":"method","name":"fields","scope":"instance","parameters":[],"visibility":"public"},{"type":"method","name":"getIterator","scope":"instance","parameters":[],"visibility":"public"},{"type":"method","name":"prepareRow","scope":"instance","parameters":[{"name":"row","type":{}}],"visibility":"public"},{"type":"method","name":"__toString","scope":"instance","parameters":[],"visibility":"public"},{"type":"method","name":"getIds","scope":"instance","parameters":[],"visibility":"public"}]}]