[{"type":"class","namespace":"\\Drupal\\migrate","meta":{"file":"\/Users\/clemens\/Sites\/drupal\/d8\/www\/core\/modules\/migrate\/src\/MigrateServiceProvider.php","output":"\/Users\/clemens\/Sites\/drupal-devs\/uml-generator-php\/animations\/drupal-8\/core\/modules\/migrate\/src\/MigrateServiceProvider.json"},"name":"MigrateServiceProvider","children":[{"type":"method","name":"alter","scope":"instance","parameters":[{"name":"container","type":{}}],"visibility":"public"}],"traits":[],"implements":["\\Drupal\\Core\\DependencyInjection\\ServiceModifierInterface"]}]