[{"type":"interface","namespace":"\\Drupal\\views_ui\\Form\\Ajax","meta":{"file":"\/Users\/clemens\/Sites\/drupal\/d8\/www\/core\/modules\/views_ui\/src\/Form\/Ajax\/ViewsFormInterface.php","output":"\/Users\/clemens\/Sites\/drupal-devs\/uml-generator-php\/animations\/drupal-8\/core\/modules\/views_ui\/src\/Form\/Ajax\/ViewsFormInterface.json"},"name":"ViewsFormInterface","children":[{"type":"method","name":"getFormKey","scope":"instance","parameters":[],"visibility":"public"},{"type":"method","name":"getFormState","scope":"instance","parameters":[{"name":"view","type":{}},{"name":"display_id","type":null},{"name":"js","type":null}],"visibility":"public"},{"type":"method","name":"getForm","scope":"instance","parameters":[{"name":"view","type":{}},{"name":"display_id","type":null},{"name":"js","type":null}],"visibility":"public"}]}]