[{"type":"class","namespace":"\\Drupal\\views\\Plugin\\views\\access","meta":{"file":"\/Users\/clemens\/Sites\/drupal\/d8\/www\/core\/modules\/views\/src\/Plugin\/views\/access\/None.php","output":"\/Users\/clemens\/Sites\/drupal-devs\/uml-generator-php\/animations\/drupal-8\/core\/modules\/views\/src\/Plugin\/views\/access\/None.json"},"name":"None","children":[{"type":"method","name":"summaryTitle","scope":"instance","parameters":[],"visibility":"public"},{"type":"method","name":"access","scope":"instance","parameters":[{"name":"account","type":{}}],"visibility":"public"},{"type":"method","name":"alterRouteDefinition","scope":"instance","parameters":[{"name":"route","type":{}}],"visibility":"public"}],"traits":[],"extends":"\\Drupal\\views\\Plugin\\views\\access\\AccessPluginBase","implements":[]}]