[{"type":"class","namespace":"\\Drupal\\tour_ui\\Routing","meta":{"file":"\/Users\/clemens\/Sites\/drupal\/d8\/www\/modules\/tour_ui\/lib\/Drupal\/tour_ui\/Routing\/TourUIController.php","output":"\/Users\/clemens\/Sites\/drupal-devs\/uml-generator-php\/animations\/drupal-8\/modules\/tour_ui\/lib\/Drupal\/tour_ui\/Routing\/TourUIController.json"},"name":"TourUIController","children":[{"type":"attribute","name":"manager","visibility":"protected","scope":"instance"},{"type":"method","name":"__construct","scope":"instance","parameters":[{"name":"manager","type":{}}],"visibility":"public"},{"type":"method","name":"listing","scope":"instance","parameters":[],"visibility":"public"},{"type":"method","name":"add","scope":"instance","parameters":[],"visibility":"public"},{"type":"method","name":"edit","scope":"instance","parameters":[{"name":"tour","type":{}}],"visibility":"public"},{"type":"method","name":"addTip","scope":"instance","parameters":[{"name":"tour","type":{}},{"name":"type","type":null}],"visibility":"public"},{"type":"method","name":"editTip","scope":"instance","parameters":[{"name":"tour","type":{}},{"name":"tip","type":null}],"visibility":"public"}],"traits":[],"implements":[]}]