[{"type":"class","namespace":"\\Drupal\\Core\\Mail\\Plugin\\Mail","meta":{"file":"\/Users\/clemens\/Sites\/drupal\/d8\/www\/core\/lib\/Drupal\/Core\/Mail\/Plugin\/Mail\/TestMailCollector.php","output":"\/Users\/clemens\/Sites\/drupal-devs\/uml-generator-php\/animations\/drupal-8\/core\/lib\/Drupal\/Core\/Mail\/Plugin\/Mail\/TestMailCollector.json"},"name":"TestMailCollector","children":[{"type":"method","name":"mail","scope":"instance","parameters":[{"name":"message","type":"array"}],"visibility":"public"}],"traits":[],"extends":"\\Drupal\\Core\\Mail\\Plugin\\Mail\\PhpMail","implements":["\\Drupal\\Core\\Mail\\MailInterface"]}]