[{"type":"interface","namespace":"\\Drupal\\Core\\Menu","meta":{"file":"\/Users\/clemens\/Sites\/drupal\/d8\/www\/core\/lib\/Drupal\/Core\/Menu\/MenuTreeStorageInterface.php","output":"\/Users\/clemens\/Sites\/drupal-devs\/uml-generator-php\/animations\/drupal-8\/core\/lib\/Drupal\/Core\/Menu\/MenuTreeStorageInterface.json"},"name":"MenuTreeStorageInterface","children":[{"type":"method","name":"maxDepth","scope":"instance","parameters":[],"visibility":"public"},{"type":"method","name":"resetDefinitions","scope":"instance","parameters":[],"visibility":"public"},{"type":"method","name":"rebuild","scope":"instance","parameters":[{"name":"definitions","type":"array"}],"visibility":"public"},{"type":"method","name":"load","scope":"instance","parameters":[{"name":"id","type":null}],"visibility":"public"},{"type":"method","name":"loadMultiple","scope":"instance","parameters":[{"name":"ids","type":"array"}],"visibility":"public"},{"type":"method","name":"loadByProperties","scope":"instance","parameters":[{"name":"properties","type":"array"}],"visibility":"public"},{"type":"method","name":"loadByRoute","scope":"instance","parameters":[{"name":"route_name","type":null},{"name":"route_parameters","type":"array"},{"name":"menu_name","type":null}],"visibility":"public"},{"type":"method","name":"save","scope":"instance","parameters":[{"name":"definition","type":"array"}],"visibility":"public"},{"type":"method","name":"delete","scope":"instance","parameters":[{"name":"id","type":null}],"visibility":"public"},{"type":"method","name":"loadTreeData","scope":"instance","parameters":[{"name":"menu_name","type":null},{"name":"parameters","type":{}}],"visibility":"public"},{"type":"method","name":"loadAllChildren","scope":"instance","parameters":[{"name":"id","type":null},{"name":"max_relative_depth","type":null}],"visibility":"public"},{"type":"method","name":"getAllChildIds","scope":"instance","parameters":[{"name":"id","type":null}],"visibility":"public"},{"type":"method","name":"loadSubtreeData","scope":"instance","parameters":[{"name":"id","type":null},{"name":"max_relative_depth","type":null}],"visibility":"public"},{"type":"method","name":"getRootPathIds","scope":"instance","parameters":[{"name":"id","type":null}],"visibility":"public"},{"type":"method","name":"getExpanded","scope":"instance","parameters":[{"name":"menu_name","type":null},{"name":"parents","type":"array"}],"visibility":"public"},{"type":"method","name":"getSubtreeHeight","scope":"instance","parameters":[{"name":"id","type":null}],"visibility":"public"},{"type":"method","name":"menuNameInUse","scope":"instance","parameters":[{"name":"menu_name","type":null}],"visibility":"public"},{"type":"method","name":"getMenuNames","scope":"instance","parameters":[],"visibility":"public"},{"type":"method","name":"countMenuLinks","scope":"instance","parameters":[{"name":"menu_name","type":null}],"visibility":"public"}]}]