[{"type":"interface","namespace":"\\Drupal\\Core\\Field","meta":{"file":"\/Users\/clemens\/Sites\/drupal\/d8\/www\/core\/lib\/Drupal\/Core\/Field\/FieldItemListInterface.php","output":"\/Users\/clemens\/Sites\/drupal-devs\/uml-generator-php\/animations\/drupal-8\/core\/lib\/Drupal\/Core\/Field\/FieldItemListInterface.json"},"name":"FieldItemListInterface","children":[{"type":"method","name":"getEntity","scope":"instance","parameters":[],"visibility":"public"},{"type":"method","name":"setLangcode","scope":"instance","parameters":[{"name":"langcode","type":null}],"visibility":"public"},{"type":"method","name":"getLangcode","scope":"instance","parameters":[],"visibility":"public"},{"type":"method","name":"getFieldDefinition","scope":"instance","parameters":[],"visibility":"public"},{"type":"method","name":"getSettings","scope":"instance","parameters":[],"visibility":"public"},{"type":"method","name":"getSetting","scope":"instance","parameters":[{"name":"setting_name","type":null}],"visibility":"public"},{"type":"method","name":"defaultAccess","scope":"instance","parameters":[{"name":"operation","type":null},{"name":"account","type":{}}],"visibility":"public"},{"type":"method","name":"filterEmptyItems","scope":"instance","parameters":[],"visibility":"public"},{"type":"method","name":"__get","scope":"instance","parameters":[{"name":"property_name","type":null}],"visibility":"public"},{"type":"method","name":"__set","scope":"instance","parameters":[{"name":"property_name","type":null},{"name":"value","type":null}],"visibility":"public"},{"type":"method","name":"__isset","scope":"instance","parameters":[{"name":"property_name","type":null}],"visibility":"public"},{"type":"method","name":"__unset","scope":"instance","parameters":[{"name":"property_name","type":null}],"visibility":"public"},{"type":"method","name":"preSave","scope":"instance","parameters":[],"visibility":"public"},{"type":"method","name":"insert","scope":"instance","parameters":[],"visibility":"public"},{"type":"method","name":"update","scope":"instance","parameters":[],"visibility":"public"},{"type":"method","name":"delete","scope":"instance","parameters":[],"visibility":"public"},{"type":"method","name":"deleteRevision","scope":"instance","parameters":[],"visibility":"public"},{"type":"method","name":"view","scope":"instance","parameters":[{"name":"display_options","type":null}],"visibility":"public"},{"type":"method","name":"defaultValuesForm","scope":"instance","parameters":[{"name":"form","type":"array"},{"name":"form_state","type":"array"}],"visibility":"public"},{"type":"method","name":"defaultValuesFormValidate","scope":"instance","parameters":[{"name":"element","type":"array"},{"name":"form","type":"array"},{"name":"form_state","type":"array"}],"visibility":"public"},{"type":"method","name":"defaultValuesFormSubmit","scope":"instance","parameters":[{"name":"element","type":"array"},{"name":"form","type":"array"},{"name":"form_state","type":"array"}],"visibility":"public"},{"type":"method","name":"processDefaultValue","scope":"classifier","parameters":[{"name":"default_value","type":null},{"name":"entity","type":{}},{"name":"definition","type":{}}],"visibility":"public"}]}]