[{"type":"class","namespace":"\\Drupal\\action","meta":{"file":"\/Users\/clemens\/Sites\/drupal\/d8\/www\/core\/modules\/action\/src\/ActionListBuilder.php","output":"\/Users\/clemens\/Sites\/drupal-devs\/uml-generator-php\/animations\/drupal-8\/core\/modules\/action\/src\/ActionListBuilder.json"},"name":"ActionListBuilder","children":[{"type":"attribute","name":"hasConfigurableActions","visibility":"protected","scope":"instance"},{"type":"attribute","name":"actionManager","visibility":"protected","scope":"instance"},{"type":"method","name":"__construct","scope":"instance","parameters":[{"name":"entity_type","type":{}},{"name":"storage","type":{}},{"name":"action_manager","type":{}}],"visibility":"public"},{"type":"method","name":"createInstance","scope":"classifier","parameters":[{"name":"container","type":{}},{"name":"entity_type","type":{}}],"visibility":"public"},{"type":"method","name":"load","scope":"instance","parameters":[],"visibility":"public"},{"type":"method","name":"buildRow","scope":"instance","parameters":[{"name":"entity","type":{}}],"visibility":"public"},{"type":"method","name":"buildHeader","scope":"instance","parameters":[],"visibility":"public"},{"type":"method","name":"getDefaultOperations","scope":"instance","parameters":[{"name":"entity","type":{}}],"visibility":"public"},{"type":"method","name":"render","scope":"instance","parameters":[],"visibility":"public"}],"traits":[],"extends":"\\Drupal\\Core\\Config\\Entity\\ConfigEntityListBuilder","implements":[]}]