[{"type":"class","namespace":"\\Drupal\\Core\\Database\\Driver\\fake","meta":{"file":"\/Users\/clemens\/Sites\/drupal\/d8\/www\/core\/lib\/Drupal\/Core\/Database\/Driver\/fake\/DatabaseRowSelect.php","output":"\/Users\/clemens\/Sites\/drupal-devs\/uml-generator-php\/animations\/drupal-8\/core\/lib\/Drupal\/Core\/Database\/Driver\/fake\/DatabaseRowSelect.json"},"name":"DatabaseRowSelect","children":[{"type":"method","name":"__construct","scope":"instance","parameters":[{"name":"row","type":"array"},{"name":"fields_with_table","type":"array"},{"name":"fields","type":"array"}],"visibility":"public"},{"type":"method","name":"getValue","scope":"instance","parameters":[{"name":"field","type":null}],"visibility":"public"}],"traits":[],"extends":"\\Drupal\\Core\\Database\\Driver\\fake\\DatabaseRow","implements":[]}]