[{"type":"class","namespace":"\\Drupal\\Core\\Extension","meta":{"file":"\/Users\/clemens\/Sites\/drupal\/d8\/www\/core\/lib\/Drupal\/Core\/Extension\/ThemeHandler.php","output":"\/Users\/clemens\/Sites\/drupal-devs\/uml-generator-php\/animations\/drupal-8\/core\/lib\/Drupal\/Core\/Extension\/ThemeHandler.json"},"name":"ThemeHandler","children":[{"type":"attribute","name":"defaultFeatures","visibility":"protected","scope":"instance"},{"type":"attribute","name":"list","visibility":"protected","scope":"instance"},{"type":"attribute","name":"configFactory","visibility":"protected","scope":"instance"},{"type":"attribute","name":"moduleHandler","visibility":"protected","scope":"instance"},{"type":"attribute","name":"state","visibility":"protected","scope":"instance"},{"type":"attribute","name":"configInstaller","visibility":"protected","scope":"instance"},{"type":"attribute","name":"infoParser","visibility":"protected","scope":"instance"},{"type":"attribute","name":"routeBuilder","visibility":"protected","scope":"instance"},{"type":"attribute","name":"extensionDiscovery","visibility":"protected","scope":"instance"},{"type":"method","name":"__construct","scope":"instance","parameters":[{"name":"config_factory","type":{}},{"name":"module_handler","type":{}},{"name":"state","type":{}},{"name":"info_parser","type":{}},{"name":"config_installer","type":{}},{"name":"route_builder","type":{}},{"name":"extension_discovery","type":{}}],"visibility":"public"},{"type":"method","name":"getDefault","scope":"instance","parameters":[],"visibility":"public"},{"type":"method","name":"setDefault","scope":"instance","parameters":[{"name":"name","type":null}],"visibility":"public"},{"type":"method","name":"enable","scope":"instance","parameters":[{"name":"theme_list","type":"array"},{"name":"enable_dependencies","type":null}],"visibility":"public"},{"type":"method","name":"disable","scope":"instance","parameters":[{"name":"theme_list","type":"array"}],"visibility":"public"},{"type":"method","name":"listInfo","scope":"instance","parameters":[],"visibility":"public"},{"type":"method","name":"addTheme","scope":"instance","parameters":[{"name":"theme","type":{}}],"visibility":"public"},{"type":"method","name":"refreshInfo","scope":"instance","parameters":[],"visibility":"public"},{"type":"method","name":"reset","scope":"instance","parameters":[],"visibility":"public"},{"type":"method","name":"rebuildThemeData","scope":"instance","parameters":[],"visibility":"public"},{"type":"method","name":"themeInfoPrefixPath","scope":"instance","parameters":[{"name":"info","type":"array"},{"name":"path","type":null}],"visibility":"protected"},{"type":"method","name":"getBaseThemes","scope":"instance","parameters":[{"name":"themes","type":"array"},{"name":"theme","type":null}],"visibility":"public"},{"type":"method","name":"doGetBaseThemes","scope":"instance","parameters":[{"name":"themes","type":"array"},{"name":"theme","type":null},{"name":"used_themes","type":null}],"visibility":"protected"},{"type":"method","name":"getExtensionDiscovery","scope":"instance","parameters":[],"visibility":"protected"},{"type":"method","name":"resetSystem","scope":"instance","parameters":[],"visibility":"protected"},{"type":"method","name":"getName","scope":"instance","parameters":[{"name":"theme","type":null}],"visibility":"public"},{"type":"method","name":"systemListReset","scope":"instance","parameters":[],"visibility":"protected"},{"type":"method","name":"clearCssCache","scope":"instance","parameters":[],"visibility":"protected"},{"type":"method","name":"themeRegistryRebuild","scope":"instance","parameters":[],"visibility":"protected"},{"type":"method","name":"systemThemeList","scope":"instance","parameters":[],"visibility":"protected"}],"traits":[],"implements":["\\Drupal\\Core\\Extension\\ThemeHandlerInterface"]}]