[{"type":"class","namespace":"\\Drupal\\Component\\Diff\\Engine","meta":{"file":"\/Users\/clemens\/Sites\/drupal\/d8\/www\/core\/lib\/Drupal\/Component\/Diff\/Engine\/DiffOpChange.php","output":"\/Users\/clemens\/Sites\/drupal-devs\/uml-generator-php\/animations\/drupal-8\/core\/lib\/Drupal\/Component\/Diff\/Engine\/DiffOpChange.json"},"name":"DiffOpChange","children":[{"type":"attribute","name":"type","visibility":"public","scope":"instance"},{"type":"method","name":"__construct","scope":"instance","parameters":[{"name":"orig","type":null},{"name":"closing","type":null}],"visibility":"public"},{"type":"method","name":"reverse","scope":"instance","parameters":[],"visibility":"public"}],"traits":[],"extends":"\\Drupal\\Component\\Diff\\Engine\\DiffOp","implements":[]}]